{
  "_class": "group",
  "booleanOperation": -1,
  "clippingMaskMode": 0,
  "do_objectID": "D6D91A26-E43A-4887-9676-3990C842DEB8",
  "exportOptions": {
    "_class": "exportOptions",
    "exportFormats": [
    ],
    "includedLayerIds": [
    ],
    "layerOptions": 0,
    "shouldTrim": false
  },
  "frame": {
    "_class": "rect",
    "constrainProportions": false,
    "height": 852,
    "width": 22,
    "x": 1248,
    "y": 48
  },
  "groupLayout": {
    "_class": "MSImmutableFreeformGroupLayout"
  },
  "hasClickThrough": false,
  "hasClippingMask": false,
  "isFixedToViewport": false,
  "isFlippedHorizontal": false,
  "isFlippedVertical": false,
  "isLocked": false,
  "isVisible": true,
  "layerListExpandedType": 0,
  "layers": [
    {
      "class": "shapeGroup",
      "id": "81D0986C-D13A-42DD-8D66-E8BDC90A687D"
    },
    {
      "class": "shapeGroup",
      "id": "5BAD2294-9518-4BFA-8790-AC55BC5E5D98"
    },
    {
      "class": "shapeGroup",
      "id": "A984E7D7-C5C7-40F8-BC9A-BAB4E602043C"
    },
    {
      "class": "shapeGroup",
      "id": "2F5854B3-FDEE-47A7-80AE-4BBA429ED46D"
    },
    {
      "class": "text",
      "id": "08C33750-5E35-4AE0-B20D-913EE2C30512"
    }
  ],
  "name": "#height-right-EA7F468D-4AE3-4C64-8731-4E56A6F82B33",
  "nameIsFixed": false,
  "resizingConstraint": 63,
  "resizingType": 0,
  "rotation": 0,
  "shouldBreakMaskChain": false,
  "style": {
    "_class": "style",
    "blur": {
      "_class": "blur",
      "center": "{0.5, 0.5}",
      "isEnabled": false,
      "motionAngle": 0,
      "radius": 10,
      "saturation": 1,
      "type": 0
    },
    "borderOptions": {
      "_class": "borderOptions",
      "dashPattern": [
      ],
      "isEnabled": true,
      "lineCapStyle": 0,
      "lineJoinStyle": 0
    },
    "borders": [
    ],
    "colorControls": {
      "_class": "colorControls",
      "brightness": 0,
      "contrast": 1,
      "hue": 0,
      "isEnabled": false,
      "saturation": 1
    },
    "contextSettings": {
      "_class": "graphicsContextSettings",
      "blendMode": 0,
      "opacity": 1
    },
    "do_objectID": "D283A2BE-4EBD-4D10-9BE9-C3BA9419A2CC",
    "endMarkerType": 0,
    "fills": [
    ],
    "innerShadows": [
    ],
    "miterLimit": 10,
    "shadows": [
    ],
    "startMarkerType": 0,
    "windingRule": 1
  }
}